Workbook

Sheet report
A1: Наименование | B1: Регистрационный номер | C1: Статус | D1: Код налогоплательщика | E1: Регион регистрации | F1: Организационно-правовая форма | G1: 2017, Среднесписочная численность работников | H1: 2018, Среднесписочная численность работников | I1: 2017, Всего поступило средств, RUB | J1: 2018, Всего поступило средств, RUB | K1: 2017, Всего использовано средств, RUB | L1: 2018, Всего использовано средств, RUB
A2: 1ПОМОГАЕТ, БФ | B2: 1167700056347 | C2: Действующая | D2: 9718005523 | E2: Москва | F2: Благотворительные фонды | G2: 0 - 5 | I2: 1533000 | J2: 3635000 | K2: 1458000 | L2: 2559000
A3: 5541 ДОБРО, БФ | B3: 1147799011612 | C3: Действующая | D3: 7743111095 | E3: Москва | F3: Благотворительные фонды | G3: 11 - 15 | H3: 51 - 100 | I3: 754602000 | J3: 248596000 | K3: 641697000 | L3: 408668000
A4: А.УСМАНОВА, ФОНД | B4: 1027729004269 | C4: Действующая | D4: 7729418938 | E4: Москва | F4: Благотворительные фонды | G4: 0 - 5 | I4: 5000000 | K4: 4516000
A5: АВИАЦИОННО-КОСМИЧЕСКИЙ ФОНД, МОФ | B5: 1037746023061 | C5: Действующая | D5: 7730175408 | E5: Москва | F5: Общественные фонды | G5: 0 - 5
A6: АДВОКАТСКАЯ ИНИЦИАТИВА, ФОНД | B6: 1037739896226 | C6: Действующая | D6: 7704502779 | E6: Москва | F6: Общественные фонды | G6: 11 - 15 | H6: 51 - 100 | I6: 27002000 | J6: 25410000 | K6: 29355000 | L6: 24228000
A7: АДЫГИ ИМ. Ю.Х. КАЛМЫКОВА, ФОНД | B7: 1117799020283 | C7: Действующая | D7: 7701167716 | E7: Москва | F7: Фонды | G7: 0 - 5 | I7: 4280000 | J7: 2880000 | K7: 4122000 | L7: 2847000
A8: АЛЕКСАНДР, БФ | B8: 1127799000262 | C8: Действующая | D8: 7718747095 | E8: Москва | F8: Благотворительные фонды | G8: 0 - 5 | I8: 1661000 | J8: 1613000 | K8: 1674000 | L8: 1701000
A9: АЛИНЫ КАБАЕВОЙ, ФОНД | B9: 1087799027007 | C9: Действующая | D9: 7731282240 | E9: Москва | F9: Благотворительные фонды | G9: 0 - 5 | I9: 67000000 | J9: 146876000 | K9: 74958000 | L9: 107775000
A10: АЛФАВИТ, БЛАГОТВОРИТЕЛЬНЫЙ ФОНД | B10: 1047796688642 | C10: Действующая | D10: 7710556980 | E10: Москва | F10: Благотворительные фонды | G10: 0 - 5
A11: АЛЬФА-ШАНС, БФ | B11: 1137799022481 | C11: Действующая | D11: 7708241493 | E11: Москва | F11: Благотворительные фонды | G11: 0 - 5 | I11: 366217000 | J11: 362116000 | K11: 363962000 | L11: 362539000
A12: АНАЛИТИЧЕСКИЙ ЦЕНТР ФОРУМ, ФОНД | B12: 1107799031801 | C12: Действующая | D12: 7706414895 | E12: Москва | F12: Общественные фонды | G12: 51 - 100 | I12: 253031000 | J12: 150000000 | K12: 256576000 | L12: 211270000
A13: АНАСТАСИЯ, БЛАГОТВОРИТЕЛЬНЫЙ ФОНД | B13: 1132300004209 | C13: Действующая | D13: 2311981014 | E13: Москва | F13: Благотворительные фонды | G13: 0 - 5 | I13: 18169000 | J13: 23911000 | K13: 15809000 | L13: 21475000
A14: АНДРЕЯ БОГОЛЮБСКОГО, ФОНД | B14: 1117799010230 | C14: Действующая | D14: 7718746380 | E14: Москва | F14: Общественные фонды | G14: 0 - 5 | J14: 473000 | L14: 473000
A15: АПОСТОЛА АНДРЕЯ ПЕРВОЗВАННОГО; ФОНД АНДРЕЯ ПЕРВОЗВАННОГО, ФОНД | B15: 1027746000446 | C15: Действующая | D15: 7704243940 | E15: Москва | F15: Общественные фонды | G15: 11 - 15 | I15: 191006000 | J15: 195326000 | K15: 207475000 | L15: 165612000
A16: АРИФМЕТИКА ДОБРА, БФ | B16: 1147799003770 | C16: Действующая | D16: 7701093849 | E16: Москва | F16: Благотворительные фонды | G16: 51 - 100 | H16: 51 - 100 | I16: 128983000 | J16: 105573000 | K16: 95513000 | L16: 107906000
A17: АРТ ФЕСТИВАЛЬ-РОЗА ВЕТРОВ, ДБФ | B17: 1027739678724 | C17: Действующая | D17: 7734211777 | E17: Москва | F17: Благотворительные фонды | G17: 0 - 5 | J17: 35643000 | L17: 34247000
A18: АРТЕМИДА, БЛАГОТВОРИТЕЛЬНЫЙ ФОНД | B18: 1157700019916 | C18: Действующая | D18: 7708276104 | E18: Москва | F18: Благотворительные фонды | G18: 0 - 5 | I18: 16977000 | J18: 43816000 | K18: 20640000 | L18: 17161000
A19: АРТИСТ, БЛАГОТВОРИТЕЛЬНЫЙ ФОНД | B19: 1087799033630 | C19: Действующая | D19: 7705520001 | E19: Москва | F19: Благотворительные фонды | G19: 0 - 5 | I19: 78588000 | J19: 90809000 | K19: 76572000 | L19: 93156000
A20: АРТЭС, КБФ | B20: 1027739859663 | C20: Действующая | D20: 7705328820 | E20: Москва | F20: Благотворительные фонды | G20: 6 - 10 | I20: 381000 | J20: 857000 | K20: 3501000 | L20: 1441000
A21: БЕЗРАЗЛИЧИЯ. НЕТ, БФ | B21: 1157700020345 | C21: Действующая | D21: 9705056954 | E21: Москва | F21: Благотворительные фонды | G21: 0 - 5 | I21: 1684000 | J21: 734000 | K21: 81000 | L21: 2416000
A22: БЕЛЫЙ ИРИС, ФОНД | B22: 1167700056270 | C22: Действующая | D22: 7721486189 | E22: Москва | F22: Благотворительные фонды | G22: 0 - 5 | J22: 7821000 | L22: 6681000
A23: БЕЛЬКАНТО, БЛАГОТВОРИТЕЛЬНЫЙ ФОНД | B23: 1067746154904 | C23: Действующая | D23: 7703578750 | E23: Москва | F23: Благотворительные фонды | G23: 6 - 10 | I23: 9631000 | J23: 6580000 | K23: 24596000 | L23: 2387000
A24: БЕНЕФИС, ФОНД | B24: 1027700084829 | C24: Действующая | D24: 7707174999 | E24: Москва | F24: Благотворительные фонды | G24: 0 - 5 | I24: 153000 | J24: 786000 | K24: 123000 | L24: 822000
A25: БИМ, ФОНД | B25: 1027700592138 | C25: Действующая | D25: 7701274845 | E25: Москва | F25: Благотворительные фонды | G25: 0 - 5 | I25: 12211000 | J25: 12871000 | K25: 12285000 | L25: 12837000
A26: БИФ ПОМОГИ.ОРГ | B26: 1057748529684 | C26: Действующая | D26: 7702579448 | E26: Москва | F26: Благотворительные фонды | G26: 0 - 5 | J26: 150571000 | L26: 163859000
A27: БЛАГО, БФ | B27: 1027700129918 | C27: Действующая | D27: 7709223761 | E27: Москва | F27: Благотворительные фонды | G27: 0 - 5 | I27: 220873000 | K27: 218348000
A28: БЛАГОВЕСТ, РОФПСППМ | B28: 1037739344169 | C28: Действующая | D28: 7704200577 | E28: Москва | F28: Общественные фонды | G28: 0 - 5 | I28: 397000 | K28: 397000
A29: БЛАГОДАТЬ, БФ | B29: 1137799022580 | C29: Действующая | D29: 7704281713 | E29: Москва | F29: Благотворительные фонды | G29: 0 - 5
A30: БЛАГОЕ ДЕЛО В СТАРЫХ ЧЕРЕМУШКАХ, БФ | B30: 1107799031560 | C30: Действующая | D30: 7727002596 | E30: Москва | F30: Благотворительные фонды | G30: 11 - 15
A31: БЛАГОКРОВ, БФ | B31: 1147799006321 | C31: Действующая | D31: 7709473761 | E31: Москва | F31: Благотворительные фонды | G31: 0 - 5 | I31: 560000 | J31: 693000 | K31: 522000 | L31: 700000
A32: БЛАГОТВОРИТЕЛЬНЫЙ ФОНД ДМИТРИЯ КОРОБКОВА | B32: 1077799021871 | C32: Действующая | D32: 7704274226 | E32: Москва | F32: Благотворительные фонды | G32: 0 - 5 | I32: 3700000 | J32: 5970000 | K32: 3400000 | L32: 4861000
A33: БЛАГОТВОРИТЕЛЬНЫЙ ФОНД ЕЛЕНЫ ОБРАЗЦОВОЙ | B33: 1127799000515 | C33: Действующая | D33: 7710479630 | E33: Москва | F33: Благотворительные фонды | G33: 6 - 10 | J33: 71730000 | L33: 66625000
A34: БЛАГОТВОРИТЕЛЬНЫЙ ФОНД ЗАБОТА О БУДУЩЕМ, НКО | B34: 1127799013572 | C34: Действующая | D34: 7704279778 | E34: Москва | F34: Благотворительные фонды | G34: 0 - 5 | I34: 3226000 | J34: 2803000 | K34: 3248000 | L34: 2921000
A35: БЛАГОТВОРИТЕЛЬНЫЙ ФОНД ИМ. МЕЙЕРХОЛЬДА | B35: 1027739480614 | C35: Действующая | D35: 7710374290 | E35: Москва | F35: Благотворительные фонды | G35: 0 - 5 | I35: 4154000 | K35: 4154000
A36: БЛАГОТВОРИТЕЛЬНЫЙ ФОНД ИМЕНИ Д. ОЙСТРАХА, НО | B36: 1057746156456 | C36: Действующая | D36: 7703541239 | E36: Москва | F36: Благотворительные фонды | G36: 0 - 5
A37: БЛАГОТВОРИТЕЛЬНЫЙ ФОНД ИМЕНИ Е.И. РЕРИХ | B37: 1037700099161 | C37: Действующая | D37: 7705205585 | E37: Москва | F37: Благотворительные фонды | G37: 0 - 5 | I37: 4290000 | J37: 1719000 | K37: 2999000 | L37: 2861000
A38: БЛАГОТВОРИТЕЛЬНЫЙ ФОНД КУЛЬТУРЫ ИМ. Ю.Н. ДОЛЖИКОВА | B38: 1167700055808 | C38: Действующая | D38: 7714385292 | E38: Москва | F38: Благотворительные фонды | G38: 0 - 5 | I38: 275000 | J38: 2765000 | K38: 111000 | L38: 513000
A39: БЛАГОТВОРИТЕЛЬНЫЙ ФОНД ЛИГИ ЗДОРОВЬЯ НАЦИИ | B39: 1037789076490 | C39: Действующая | D39: 7706518132 | E39: Москва | F39: Благотворительные фонды | G39: 11 - 15 | I39: 13640000 | J39: 19783000 | K39: 2813000 | L39: 15449000
A40: БЛАГОТВОРИТЕЛЬНЫЙ ФОНД ЛИЦО РЕБЕНКА, НО | B40: 1037701912720 | C40: Действующая | D40: 7701340199 | E40: Москва | F40: Благотворительные фонды | G40: 0 - 5 | I40: 13220000 | J40: 14404000 | K40: 12976000 | L40: 13168000
A41: БЛАГОТВОРИТЕЛЬНЫЙ ФОНД НАТАЛИИ КУЗЬМИНОЙ | B41: 1067799022840 | C41: Действующая | D41: 7704272540 | E41: Москва | F41: Благотворительные фонды | G41: 0 - 5 | I41: 1782000 | J41: 1621000 | K41: 1655000 | L41: 1621000
A42: БЛАГОТВОРИТЕЛЬНЫЙ ФОНД ПО ВОССТАНОВЛЕНИЮ ВОСКРЕСЕНСКОГО НОВО-ИЕРУСАЛИМСКОГО МОНАСТЫРЯ | B42: 1087799035796 | C42: Действующая | D42: 7705520019 | E42: Москва | F42: Благотворительные фонды | G42: 0 - 5 | I42: 144895000 | J42: 120695000 | K42: 178280000 | L42: 147215000
A43: БЛАГОТВОРИТЕЛЬНЫЙ ФОНД ПОДДЕРЖКИ И РАЗВИТИЯ РУССКОЙ ЭКОНОМИКИ | B43: 1127799010690 | C43: Действующая | D43: 7722400709 | E43: Москва | F43: Благотворительные фонды | G43: 0 - 5 | I43: 45304000 | J43: 42993000 | K43: 46293000 | L43: 38545000
A44: БЛАГОТВОРИТЕЛЬНЫЙ ФОНД ПОМОЩНИК И ПОКРОВИТЕЛЬ | B44: 1057601585030 | C44: Действующая | D44: 7609018818 | E44: Москва | F44: Благотворительные фонды | G44: 0 - 5
A45: БЛАГОТВОРИТЕЛЬНЫЙ ФОНД ПРОФИЛАКТИКИ СОЦИАЛЬНОГО СИРОТСТВА | B45: 1117799012319 | C45: Действующая | D45: 7734269752 | E45: Москва | F45: Благотворительные фонды | G45: 6 - 10 | I45: 9916000 | J45: 14935000 | K45: 14554000 | L45: 14885000
A46: БЛАГОТВОРИТЕЛЬНЫЙ ФОНД РАЗВИТИЯ МШЭ МГУ | B46: 1057746008704 | C46: Действующая | D46: 7727531350 | E46: Москва | F46: Благотворительные фонды | G46: 0 - 5 | I46: 30155000 | J46: 25752000 | K46: 35079000 | L46: 26558000
A47: БЛАГОТВОРИТЕЛЬНЫЙ ФОНД РЕАБИЛИТАЦИИ БОЛЬНЫХ НАРКОМАНИЕЙ (НЕКОММЕРЧЕСКАЯ ОРГАНИЗАЦИЯ) | B47: 1027739327208 | C47: Действующая | D47: 7708102267 | E47: Москва | F47: Благотворительные фонды | G47: 0 - 5
A48: БЛАГОТВОРИТЕЛЬНЫЙ ФОНД СВЯТИТЕЛЯ НИКОЛАЯ ЧУДОТВОРЦА, НО | B48: 1027700096126 | C48: Действующая | D48: 7707307350 | E48: Москва | F48: Благотворительные фонды | G48: 0 - 5 | I48: 3091000 | J48: 2251000 | K48: 5694000 | L48: 2379000
A49: БЛАГОТВОРИТЕЛЬНЫЙ ФОНД СВЯТОЙ ГОРЫ АФОН | B49: 1057748254211 | C49: Действующая | D49: 7705686991 | E49: Москва | F49: Благотворительные фонды | G49: 0 - 5 | I49: 4737000 | J49: 2316000 | K49: 4219000 | L49: 2777000
A50: БЛАГОТВОРИТЕЛЬНЫЙ ФОНД СЕРГЕЯ САРКИСОВА | B50: 1067799021850 | C50: Действующая | D50: 7710475435 | E50: Москва | F50: Благотворительные фонды | G50: 0 - 5 | I50: 2577000 | J50: 366000 | K50: 548000 | L50: 531000
A51: БОЛЬШАЯ ПЕРЕМЕНА, БФ | B51: 1027725001732 | C51: Действующая | D51: 7725203709 | E51: Москва | F51: Благотворительные фонды | G51: 0 - 5 | I51: 28095000 | J51: 35972000 | K51: 29532000 | L51: 34057000
A52: БОРОВИКА, ФОНД | B52: 1107799019261 | C52: Действующая | D52: 7727290305 | E52: Москва | F52: Благотворительные фонды | G52: 0 - 5 | I52: 3316000 | J52: 1089000 | K52: 12956000 | L52: 13850000
A53: БРАТСТВО, БЛАГОТВОРИТЕЛЬНЫЙ ФОНД | B53: 1037739017414 | C53: Действующая | D53: 7708159270 | E53: Москва | F53: Благотворительные фонды | G53: 0 - 5 | I53: 150000 | J53: 1500000 | K53: 120000 | L53: 1800000
A54: БЛАГОТВОРИТЕЛЬНЫЙ ФОНД ИМЕНИ ПРИМАКОВА Е.М. | B54: 1037739365135 | C54: Действующая | D54: 7701295193 | E54: Москва | F54: Благотворительные фонды | G54: 0 - 5 | I54: 10334000 | J54: 4472000 | K54: 12605000 | L54: 8266000
A55: БЛАГОТВОРИТЕЛЬНЫЙ ФОНД МАРКА КАУФМАНА | B55: 1027700436829 | C55: Действующая | D55: 7706274310 | E55: Москва | F55: Благотворительные фонды | G55: 0 - 5 | I55: 2185000 | J55: 1850000 | K55: 3304000 | L55: 2283000
A56: БЛАГОТВОРИТЕЛЬНЫЙ ФОНД РАЗВИТИЯ ФИЛАНТРОПИИ | B56: 1127799000560 | C56: Действующая | D56: 7701168082 | E56: Москва | F56: Благотворительные фонды | G56: 11 - 15 | H56: 51 - 100 | I56: 192489000 | J56: 192711000 | K56: 226637000 | L56: 181373000
A57: БУДЕМ ЖИТЬ! ИМ. М.БАСЮКА, ФОНД | B57: 1087799008956 | C57: Действующая | D57: 7706413531 | E57: Москва | F57: Благотворительные фонды | G57: 0 - 5 | I57: 1532000 | J57: 301000 | K57: 5507000 | L57: 71000
A58: БУДУЩЕЕ ДЛЯ ДЕТЕЙ!, БФ | B58: 1147799005012 | C58: Действующая | D58: 7743110976 | E58: Москва | F58: Благотворительные фонды | G58: 0 - 5 | I58: 2640000 | K58: 2646000
A59: БУДУЩЕЕ-СЕГОДНЯ, БФ | B59: 1137799023658 | C59: Действующая | D59: 7703480811 | E59: Москва | F59: Благотворительные фонды | G59: 0 - 5 | I59: 4184000 | J59: 2544000 | K59: 14307000 | L59: 14032000
A60: БУМЕРАНГ, БЛАГОТВОРИТЕЛЬНЫЙ ФОНД | B60: 1147799018036 | C60: Действующая | D60: 7718490146 | E60: Москва | F60: Благотворительные фонды | G60: 0 - 5 | I60: 10000 | J60: 230000 | K60: 19000 | L60: 107000
A61: БФ ГИМНАЗИИ № 1520 ИМЕНИ КАПЦОВЫХ | B61: 1147799010402 | C61: Действующая | D61: 7725352796 | E61: Москва | F61: Благотворительные фонды | G61: 0 - 5 | I61: 778000 | J61: 537000 | K61: 1170000 | L61: 534000
A62: БФ ИМ.ГЕРОЯ РФ ГРОМОВА С.С. | B62: 1047797042127 | C62: Действующая | D62: 7730517620 | E62: Москва | F62: Благотворительные фонды | G62: 0 - 5 | I62: 15000 | J62: 11000 | K62: 11000 | L62: 13000
A63: БФ МАРИНЫ СИЛКОВОЙ | B63: 1167700058657 | C63: Действующая | D63: 9729011399 | E63: Москва | F63: Благотворительные фонды | G63: 0 - 5 | I63: 664000 | J63: 270000 | K63: 629000 | L63: 334000
A64: БФ МОЛОДЕЖНЫХ ПРОГРАММ | B64: 1056405440772 | C64: Действующая | D64: 6454075223 | E64: Москва | F64: Благотворительные фонды | G64: 0 - 5 | I64: 23151000 | J64: 29488000 | K64: 99038000 | L64: 52894000
A65: БФ МЭШ, ФОНД | B65: 1037700206235 | C65: Действующая | D65: 7703259257 | E65: Москва | F65: Благотворительные фонды | G65: 0 - 5 | I65: 2781000 | J65: 3389000 | K65: 1269000 | L65: 1707000
A66: БФ НАША СЕМЬЯ | B66: 1077799003721 | C66: Действующая | D66: 7701359055 | E66: Москва | F66: Благотворительные фонды | G66: 0 - 5 | I66: 709000 | J66: 821000 | K66: 851000 | L66: 345000
A67: БФ ПОМОЩИ БОЛЬНЫМ С ХИРУРГИЧЕСКИМИ И ИНЫМИ ТЯЖЕЛЫМИ ЗАБОЛЕВАНИЯМИ | B67: 1157700010995 | C67: Действующая | D67: 9705044282 | E67: Москва | F67: Благотворительные фонды | G67: 0 - 5 | I67: 6450000 | J67: 8122000 | K67: 6312000 | L67: 8140000
A68: БФ СВ. ПРАВ. ИОАННА КРОНШТАДТСКОГО | B68: 1117799015432 | C68: Действующая | D68: 7707490232 | E68: Москва | F68: Благотворительные фонды | G68: 6 - 10 | I68: 7612000 | J68: 9624000 | K68: 7401000 | L68: 10652000
A69: БФ СВ.ТАТИАНЫ | B69: 1167700069240 | C69: Действующая | D69: 7726389492 | E69: Москва | F69: Благотворительные фонды | G69: 0 - 5 | J69: 70000 | L69: 1000
A70: БФ СОЦИАЛЬНОГО РАЗВИТИЯ РЕГИОНОВ | B70: 1066454041895 | C70: Действующая | D70: 6454079387 | E70: Москва | F70: Благотворительные фонды | G70: 0 - 5 | I70: 172000 | J70: 33000 | K70: 245000 | L70: 3202000
A71: БФ СОЦИАЛЬНОЙ ПОДДЕРЖКИ ВЕТЕРАНОВ ТАМОЖЕННОЙ СЛУЖБЫ | B71: 1027739913420 | C71: Действующая | D71: 7701236991 | E71: Москва | F71: Благотворительные фонды | G71: 0 - 5 | I71: 110000 | K71: 115000
A72: БФ ЦССКН | B72: 1167700052453 | C72: Действующая | D72: 7702398089 | E72: Москва | F72: Благотворительные фонды | G72: 0 - 5 | I72: 1650000 | J72: 50000 | K72: 2197000
A73: БФПСД | B73: 1097799033859 | C73: Действующая | D73: 7703394376 | E73: Москва | F73: Благотворительные фонды | G73: 0 - 5 | I73: 11611000 | J73: 12269000 | L73: 10555000
A74: БЭЛА. ДЕТИ-БАБОЧКИ, БФ | B74: 1117799003794 | C74: Действующая | D74: 7718002430 | E74: Москва | F74: Благотворительные фонды | G74: 11 - 15 | I74: 97403000 | J74: 142176000 | K74: 62297000 | L74: 120946000
A75: БЮРО ДОБРЫХ ДЕЛ, БЛАГОТВОРИТЕЛЬНЫЙ ФОНД | B75: 1127799011856 | C75: Действующая | D75: 7705520900 | E75: Москва | F75: Благотворительные фонды | G75: 0 - 5 | I75: 18068000 | J75: 16185000 | K75: 17711000 | L75: 14211000
A76: В ОТВЕТЕ ЗА БУДУЩЕЕ, БФ | B76: 1137799015750 | C76: Действующая | D76: 7707491660 | E76: Москва | F76: Благотворительные фонды | G76: 0 - 5 | I76: 19792000 | J76: 18419000 | K76: 30402000 | L76: -19174000
A77: В ТВОИХ РУКАХ, БФ | B77: 1127799023527 | C77: Действующая | D77: 7718748155 | E77: Москва | F77: Благотворительные фонды | G77: 0 - 5 | J77: 7241000 | L77: 7354000
A78: БЛАГОТВОРИТЕЛЬНЫЙ ФОНД ВЕТЕРАНОВ СПОРТА Г.МОСКВЫ | B78: 1027739739400 | C78: Действующая | D78: 7711076916 | E78: Москва | F78: Благотворительные фонды | G78: 0 - 5 | I78: 3514000 | J78: 2174000 | K78: 3452000 | L78: 2349000
A79: ВАХТАНГОВСКАЯ ШКОЛА, БФ | B79: 1047796054459 | C79: Действующая | D79: 7704511413 | E79: Москва | F79: Благотворительные фонды | G79: 0 - 5 | I79: 6800000 | J79: 19469000 | K79: 5647000 | L79: 20516000
A80: ВЕРА, БЛАГОТВОРИТЕЛЬНЫЙ ФОНД | B80: 1067799030826 | C80: Действующая | D80: 7724296034 | E80: Москва | F80: Благотворительные фонды | G80: 51 - 100 | H80: 51 - 100 | I80: 514068000 | J80: 392217000 | K80: 442917000 | L80: 391510000
A81: ВЕРШИНА СПОРТА, БЛАГОТВОРИТЕЛЬНЫЙ ФОНД | B81: 1117799005390 | C81: Действующая | D81: 7704278358 | E81: Москва | F81: Благотворительные фонды | G81: 0 - 5 | I81: 13390000 | J81: 22650000 | K81: 13674000 | L81: 21499000
A82: ВЕРШИНА, БФ | B82: 1117800018159 | C82: Действующая | D82: 7801350345 | E82: Москва | F82: Благотворительные фонды | G82: 0 - 5
A83: ВЕТЕРАН НЕФТЕГАЗСТРОЯ ИМ. Б.Е. ЩЕРБИНЫ, ФОНД | B83: 1037739738453 | C83: Действующая | D83: 7706001256 | E83: Москва | F83: Благотворительные фонды | G83: 0 - 5 | I83: 12594000 | J83: 8552000 | K83: 10451000 | L83: 7688000
A84: ВЕТЕРАНОВ ПОДРАЗДЕЛЕНИЙ ЭКОНОМИЧЕСКОЙ БЕЗОПАСНОСТИ ОРГАНОВ ВНУТРЕННИХ ДЕЛ, ФОНД | B84: 1087799030615 | C84: Действующая | D84: 7709441897 | E84: Москва | F84: Общественные фонды | G84: 0 - 5 | I84: 12980000 | J84: 2611000 | K84: 9158000 | L84: 6293000
A85: ВЕТЕРАНЫ ЛУБЯНКИ, РОФ | B85: 1037739059874 | C85: Действующая | D85: 7737123310 | E85: Москва | F85: Общественные фонды | G85: 11 - 15 | I85: 3425000 | J85: 2355000 | K85: 3667000 | L85: 1979000
A86: ВИКТОРИЯ, БДФ | B86: 1047796863179 | C86: Действующая | D86: 7704537281 | E86: Москва | F86: Благотворительные фонды | G86: 11 - 15 | I86: 66620000 | J86: 66560000 | K86: 66674000 | L86: 89127000
A87: ВИНЗАВОД, ФОНД | B87: 1087799006570 | C87: Действующая | D87: 7709441456 | E87: Москва | F87: Благотворительные фонды | G87: 201 - 250 | I87: 77367000 | J87: 46773000 | K87: 67628000 | L87: 55370000
A88: ВКЛАД В БУДУЩЕЕ | B88: 1157700017518 | C88: Действующая | D88: 7736255272 | E88: Москва | F88: Благотворительные фонды | G88: 0 - 5 | I88: 269412000 | J88: 576169000 | K88: 251203000 | L88: 337138000
A89: ВМЕСТЕ МЫ МОЖЕМ, БЛАГОТВОРИТЕЛЬНЫЙ ФОНД | B89: 1027739589052 | C89: Действующая | D89: 7715043870 | E89: Москва | F89: Благотворительные фонды | G89: 0 - 5 | I89: 69000 | J89: 165000 | K89: 150000 | L89: 128000
A90: ВМЕСТЕ ПРОТИВ РАКА, ФОНД | B90: 1097799007492 | C90: Действующая | D90: 7704275879 | E90: Москва | F90: Общественные фонды | G90: 51 - 100 | I90: 50019000 | J90: 47520000 | K90: 41433000 | L90: 60058000
A91: ВО ИМЯ АРХАНГЕЛА ГАВРИИЛА, ФОНД | B91: 1137799009094 | C91: Действующая | D91: 7724301534 | E91: Москва | F91: Благотворительные фонды | G91: 0 - 5 | I91: 7416000 | J91: 10138000 | K91: 7176000 | L91: 10392000
A92: ВО ИМЯ ЖИЗНИ, БЛАГОТВОРИТЕЛЬНЫЙ ФОНД | B92: 1077799002820 | C92: Действующая | D92: 7719286880 | E92: Москва | F92: Благотворительные фонды | G92: 0 - 5 | I92: 3539000 | J92: 14432000 | K92: 6026000 | L92: 13461000
A93: ВОЗМОЖНОСТЬ, БФ | B93: 1047796761484 | C93: Действующая | D93: 7721516764 | E93: Москва | F93: Благотворительные фонды | G93: 0 - 5 | I93: 1231000 | J93: 825000 | K93: 1229000 | L93: 846000
A94: ВОЛОНТЕРЫ В ПОМОЩЬ ДЕТЯМ-СИРОТАМ, БФ | B94: 1077799002490 | C94: Действующая | D94: 7706412841 | E94: Москва | F94: Благотворительные фонды | G94: 101 - 150 | H94: 51 - 100 | I94: 82558000 | J94: 81438000 | K94: 71662000 | L94: 80312000
A95: ВОЛЬНОЕ ДЕЛО, НФ | B95: 1027701021589 | C95: Действующая | D95: 7701318997 | E95: Москва | F95: Фонды | G95: 0 - 5 | I95: 9431000 | J95: 58973000 | K95: 33219000 | L95: 57765000
A96: ВОСКРЕСЕНИЕ, БФ | B96: 1047796109327 | C96: Действующая | D96: 7701525175 | E96: Москва | F96: Благотворительные фонды | G96: 0 - 5 | I96: 1728000 | J96: 1104000 | K96: 1197000 | L96: 905000
A97: ВПЕРЕД, РОФ | B97: 1037739032858 | C97: Действующая | D97: 7715185698 | E97: Москва | F97: Общественные фонды | G97: 0 - 5 | I97: 1428000 | J97: 1337000 | K97: 1425000 | L97: 1351000
A98: ВРАЧЕБНОЕ БРАТСТВО, БФ | B98: 1117799002420 | C98: Действующая | D98: 7710478958 | E98: Москва | F98: Благотворительные фонды | G98: 0 - 5 | I98: 7719000 | J98: 8272000 | K98: 7142000 | L98: 8521000
A99: ВСЕМИРНАЯ ЭСТАФЕТА ГАРМОНИИ, ФСКС | B99: 1107799017996 | C99: Действующая | D99: 7713387843 | E99: Москва | F99: Общественные фонды | G99: 0 - 5 | J99: 9000 | L99: 8000
A100: ВТБ-СТРАНА, БФ | B100: 1067799023632 | C100: Действующая | D100: 7702368944 | E100: Москва | F100: Благотворительные фонды | G100: 0 - 5 | J100: 7807000 | L100: 8391000
...

Sheet report2
A1: ссч | B1: доходы | C1: расходы | D1: размер | E1: ссч(примерное) | F1: финансовый результат | G1: доход на сотрудника | H1: прибыль на сотрудника
A2: 0 - 5 | B2: 1533000 | C2: 1458000 | D2: =VLOOKUP(A2,Лист2!A:E,5,0) -> малые | E2: =VLOOKUP(A2,Лист2!A:E,4,0) -> 2.5 | F2: =B2-C2 -> 75000 | G2: =B2/E2 -> 613200 | H2: =F2/E2 -> 30000
A3: 11 - 15 | B3: 754602000 | C3: 641697000 | D3: =VLOOKUP(A3,Лист2!A:E,5,0) -> малые | E3: =VLOOKUP(A3,Лист2!A:E,4,0) -> 13 | F3: =B3-C3 -> 112905000 | G3: =B3/E3 -> 58046308 | H3: =F3/E3 -> 8685000
A4: 0 - 5 | B4: 5000000 | C4: 4516000 | D4: =VLOOKUP(A4,Лист2!A:E,5,0) -> малые | E4: =VLOOKUP(A4,Лист2!A:E,4,0) -> 2.5 | F4: =B4-C4 -> 484000 | G4: =B4/E4 -> 2000000 | H4: =F4/E4 -> 193600
A5: 11 - 15 | B5: 27002000 | C5: 29355000 | D5: =VLOOKUP(A5,Лист2!A:E,5,0) -> малые | E5: =VLOOKUP(A5,Лист2!A:E,4,0) -> 13 | F5: =B5-C5 -> -2353000 | G5: =B5/E5 -> 2077076.9 | H5: =F5/E5 -> -181000
A6: 0 - 5 | B6: 4280000 | C6: 4122000 | D6: =VLOOKUP(A6,Лист2!A:E,5,0) -> малые | E6: =VLOOKUP(A6,Лист2!A:E,4,0) -> 2.5 | F6: =B6-C6 -> 158000 | G6: =B6/E6 -> 1712000 | H6: =F6/E6 -> 63200
A7: 0 - 5 | B7: 1661000 | C7: 1674000 | D7: =VLOOKUP(A7,Лист2!A:E,5,0) -> малые | E7: =VLOOKUP(A7,Лист2!A:E,4,0) -> 2.5 | F7: =B7-C7 -> -13000 | G7: =B7/E7 -> 664400 | H7: =F7/E7 -> -5200
A8: 0 - 5 | B8: 67000000 | C8: 74958000 | D8: =VLOOKUP(A8,Лист2!A:E,5,0) -> малые | E8: =VLOOKUP(A8,Лист2!A:E,4,0) -> 2.5 | F8: =B8-C8 -> -7958000 | G8: =B8/E8 -> 26800000 | H8: =F8/E8 -> -3183200
A9: 0 - 5 | B9: 366217000 | C9: 363962000 | D9: =VLOOKUP(A9,Лист2!A:E,5,0) -> малые | E9: =VLOOKUP(A9,Лист2!A:E,4,0) -> 2.5 | F9: =B9-C9 -> 2255000 | G9: =B9/E9 -> 146486800 | H9: =F9/E9 -> 902000
A10: 51 - 100 | B10: 253031000 | C10: 256576000 | D10: =VLOOKUP(A10,Лист2!A:E,5,0) -> средние | E10: =VLOOKUP(A10,Лист2!A:E,4,0) -> 75.5 | F10: =B10-C10 -> -3545000 | G10: =B10/E10 -> 3351404 | H10: =F10/E10 -> -46953.642
A11: 0 - 5 | B11: 18169000 | C11: 15809000 | D11: =VLOOKUP(A11,Лист2!A:E,5,0) -> малые | E11: =VLOOKUP(A11,Лист2!A:E,4,0) -> 2.5 | F11: =B11-C11 -> 2360000 | G11: =B11/E11 -> 7267600 | H11: =F11/E11 -> 944000
A12: 11 - 15 | B12: 191006000 | C12: 207475000 | D12: =VLOOKUP(A12,Лист2!A:E,5,0) -> малые | E12: =VLOOKUP(A12,Лист2!A:E,4,0) -> 13 | F12: =B12-C12 -> -16469000 | G12: =B12/E12 -> 14692769 | H12: =F12/E12 -> -1266846.2
A13: 51 - 100 | B13: 128983000 | C13: 95513000 | D13: =VLOOKUP(A13,Лист2!A:E,5,0) -> средние | E13: =VLOOKUP(A13,Лист2!A:E,4,0) -> 75.5 | F13: =B13-C13 -> 33470000 | G13: =B13/E13 -> 1708384.1 | H13: =F13/E13 -> 443311.26
... A1771: 201 - 250 | B1771: 995636000 | C1771: 985164000 | D1771: =VLOOKUP(A1771,Лист2!A:E,5,0) -> крупные | E1771: =VLOOKUP(A1771,Лист2!A:E,4,0) -> 225.5 | F1771: =B1771-C1771 -> 10472000 | G1771: =B1771/E1771 -> 4415237.3 | H1771: =F1771/E1771 -> 46439.024

Sheet report3
A1: ссч | B1: доходы | C1: расходы | D1: размер | E1: ссч(примерное) | F1: финансовый результат | G1: доход на сотрудника | H1: прибыль на сотрудника
A2: 0 - 5 | B2: 1533000 | C2: 1458000 | D2: =VLOOKUP(A2,Лист2!A:E,5,0) -> малые | E2: =VLOOKUP(A2,Лист2!A:E,4,0) -> 2.5 | F2: =B2-C2 -> 75000 | G2: =B2/E2 -> 613200 | H2: =F2/E2 -> 30000
A3: 11 - 15 | B3: 754602000 | C3: 641697000 | D3: =VLOOKUP(A3,Лист2!A:E,5,0) -> малые | E3: =VLOOKUP(A3,Лист2!A:E,4,0) -> 13 | F3: =B3-C3 -> 112905000 | G3: =B3/E3 -> 58046308 | H3: =F3/E3 -> 8685000
A4: 0 - 5 | B4: 5000000 | C4: 4516000 | D4: =VLOOKUP(A4,Лист2!A:E,5,0) -> малые | E4: =VLOOKUP(A4,Лист2!A:E,4,0) -> 2.5 | F4: =B4-C4 -> 484000 | G4: =B4/E4 -> 2000000 | H4: =F4/E4 -> 193600
A5: 11 - 15 | B5: 27002000 | C5: 29355000 | D5: =VLOOKUP(A5,Лист2!A:E,5,0) -> малые | E5: =VLOOKUP(A5,Лист2!A:E,4,0) -> 13 | F5: =B5-C5 -> -2353000 | G5: =B5/E5 -> 2077076.9 | H5: =F5/E5 -> -181000
A6: 0 - 5 | B6: 4280000 | C6: 4122000 | D6: =VLOOKUP(A6,Лист2!A:E,5,0) -> малые | E6: =VLOOKUP(A6,Лист2!A:E,4,0) -> 2.5 | F6: =B6-C6 -> 158000 | G6: =B6/E6 -> 1712000 | H6: =F6/E6 -> 63200
A7: 0 - 5 | B7: 1661000 | C7: 1674000 | D7: =VLOOKUP(A7,Лист2!A:E,5,0) -> малые | E7: =VLOOKUP(A7,Лист2!A:E,4,0) -> 2.5 | F7: =B7-C7 -> -13000 | G7: =B7/E7 -> 664400 | H7: =F7/E7 -> -5200
A8: 0 - 5 | B8: 67000000 | C8: 74958000 | D8: =VLOOKUP(A8,Лист2!A:E,5,0) -> малые | E8: =VLOOKUP(A8,Лист2!A:E,4,0) -> 2.5 | F8: =B8-C8 -> -7958000 | G8: =B8/E8 -> 26800000 | H8: =F8/E8 -> -3183200
A9: 0 - 5 | B9: 366217000 | C9: 363962000 | D9: =VLOOKUP(A9,Лист2!A:E,5,0) -> малые | E9: =VLOOKUP(A9,Лист2!A:E,4,0) -> 2.5 | F9: =B9-C9 -> 2255000 | G9: =B9/E9 -> 146486800 | H9: =F9/E9 -> 902000
A10: 51 - 100 | B10: 253031000 | C10: 256576000 | D10: =VLOOKUP(A10,Лист2!A:E,5,0) -> средние | E10: =VLOOKUP(A10,Лист2!A:E,4,0) -> 75.5 | F10: =B10-C10 -> -3545000 | G10: =B10/E10 -> 3351404 | H10: =F10/E10 -> -46953.642
A11: 0 - 5 | B11: 18169000 | C11: 15809000 | D11: =VLOOKUP(A11,Лист2!A:E,5,0) -> малые | E11: =VLOOKUP(A11,Лист2!A:E,4,0) -> 2.5 | F11: =B11-C11 -> 2360000 | G11: =B11/E11 -> 7267600 | H11: =F11/E11 -> 944000
A12: 11 - 15 | B12: 191006000 | C12: 207475000 | D12: =VLOOKUP(A12,Лист2!A:E,5,0) -> малые | E12: =VLOOKUP(A12,Лист2!A:E,4,0) -> 13 | F12: =B12-C12 -> -16469000 | G12: =B12/E12 -> 14692769 | H12: =F12/E12 -> -1266846.2
A13: 51 - 100 | B13: 128983000 | C13: 95513000 | D13: =VLOOKUP(A13,Лист2!A:E,5,0) -> средние | E13: =VLOOKUP(A13,Лист2!A:E,4,0) -> 75.5 | F13: =B13-C13 -> 33470000 | G13: =B13/E13 -> 1708384.1 | H13: =F13/E13 -> 443311.26
... A1720: 0 - 5 | B1720: 10000 | C1720: 10000 | D1720: =VLOOKUP(A1720,Лист2!A:E,5,0) -> малые | E1720: =VLOOKUP(A1720,Лист2!A:E,4,0) -> 2.5 | F1720: =B1720-C1720 -> 0 | G1720: =B1720/E1720 -> 4000 | H1720: =F1720/E1720 -> 0

Sheet report4
A1: регион | B1: ссч | C1: доходы | D1: расходы | E1: размер | F1: ссч(примерное) | G1: финансовый результат | H1: доход на сотрудника | I1: прибыль на сотрудника
A2: Москва | B2: 0 - 5 | C2: 1533000 | D2: 1458000 | E2: малые | F2: 2.5 | G2: 75000 | H2: 613200 | I2: 30000
A3: Москва | B3: 11 - 15 | C3: 754602000 | D3: 641697000 | E3: малые | F3: 13 | G3: 112905000 | H3: 58046308 | I3: 8685000
A4: Москва | B4: 0 - 5 | C4: 5000000 | D4: 4516000 | E4: малые | F4: 2.5 | G4: 484000 | H4: 2000000 | I4: 193600
A5: Москва | B5: 11 - 15 | C5: 27002000 | D5: 29355000 | E5: малые | F5: 13 | G5: -2353000 | H5: 2077076.9 | I5: -181000
A6: Москва | B6: 0 - 5 | C6: 4280000 | D6: 4122000 | E6: малые | F6: 2.5 | G6: 158000 | H6: 1712000 | I6: 63200
A7: Москва | B7: 0 - 5 | C7: 1661000 | D7: 1674000 | E7: малые | F7: 2.5 | G7: -13000 | H7: 664400 | I7: -5200
A8: Москва | B8: 0 - 5 | C8: 67000000 | D8: 74958000 | E8: малые | F8: 2.5 | G8: -7958000 | H8: 26800000 | I8: -3183200
A9: Москва | B9: 0 - 5 | C9: 366217000 | D9: 363962000 | E9: малые | F9: 2.5 | G9: 2255000 | H9: 146486800 | I9: 902000
A10: Москва | B10: 51 - 100 | C10: 253031000 | D10: 256576000 | E10: средние | F10: 75.5 | G10: -3545000 | H10: 3351404 | I10: -46953.642
A11: Москва | B11: 0 - 5 | C11: 18169000 | D11: 15809000 | E11: малые | F11: 2.5 | G11: 2360000 | H11: 7267600 | I11: 944000
A12: Москва | B12: 11 - 15 | C12: 191006000 | D12: 207475000 | E12: малые | F12: 13 | G12: -16469000 | H12: 14692769 | I12: -1266846.2
A13: Москва | B13: 51 - 100 | C13: 128983000 | D13: 95513000 | E13: средние | F13: 75.5 | G13: 33470000 | H13: 1708384.1 | I13: 443311.26
... A1771: Красноярский край | B1771: 201 - 250 | C1771: 995636000 | D1771: 985164000 | E1771: крупные | F1771: 225.5 | G1771: 10472000 | H1771: 4415237.3 | I1771: 46439.024

Sheet report5
A1: Организационно-правовая форма | B1: 2017, Среднесписочная численность работников | C1: 2017, Всего поступило средств, RUB | D1: 2017, Всего использовано средств, RUB | E1: размер | F1: ссч примерное | G1: финансовый результат | H1: доход на сотрудника | I1: прибыль на сотрудника
A2: Благотворительные фонды | B2: 0 - 5 | C2: 1533000 | D2: 1458000 | E2: =VLOOKUP(B2,Лист2!A:E,5,0) -> малые | F2: =VLOOKUP(B2,Лист2!A:E,4,0) -> 2.5 | G2: =C2-D2 -> 75000 | H2: =C2/F2 -> 613200 | I2: =G2/F2 -> 30000
A3: Благотворительные фонды | B3: 11 - 15 | C3: 754602000 | D3: 641697000 | E3: =VLOOKUP(B3,Лист2!A:E,5,0) -> малые | F3: =VLOOKUP(B3,Лист2!A:E,4,0) -> 13 | G3: =C3-D3 -> 112905000 | H3: =C3/F3 -> 58046308 | I3: =G3/F3 -> 8685000
A4: Благотворительные фонды | B4: 0 - 5 | C4: 5000000 | D4: 4516000 | E4: =VLOOKUP(B4,Лист2!A:E,5,0) -> малые | F4: =VLOOKUP(B4,Лист2!A:E,4,0) -> 2.5 | G4: =C4-D4 -> 484000 | H4: =C4/F4 -> 2000000 | I4: =G4/F4 -> 193600
A5: Общественные фонды | B5: 11 - 15 | C5: 27002000 | D5: 29355000 | E5: =VLOOKUP(B5,Лист2!A:E,5,0) -> малые | F5: =VLOOKUP(B5,Лист2!A:E,4,0) -> 13 | G5: =C5-D5 -> -2353000 | H5: =C5/F5 -> 2077076.9 | I5: =G5/F5 -> -181000
A6: Фонды | B6: 0 - 5 | C6: 4280000 | D6: 4122000 | E6: =VLOOKUP(B6,Лист2!A:E,5,0) -> малые | F6: =VLOOKUP(B6,Лист2!A:E,4,0) -> 2.5 | G6: =C6-D6 -> 158000 | H6: =C6/F6 -> 1712000 | I6: =G6/F6 -> 63200
A7: Благотворительные фонды | B7: 0 - 5 | C7: 1661000 | D7: 1674000 | E7: =VLOOKUP(B7,Лист2!A:E,5,0) -> малые | F7: =VLOOKUP(B7,Лист2!A:E,4,0) -> 2.5 | G7: =C7-D7 -> -13000 | H7: =C7/F7 -> 664400 | I7: =G7/F7 -> -5200
A8: Благотворительные фонды | B8: 0 - 5 | C8: 67000000 | D8: 74958000 | E8: =VLOOKUP(B8,Лист2!A:E,5,0) -> малые | F8: =VLOOKUP(B8,Лист2!A:E,4,0) -> 2.5 | G8: =C8-D8 -> -7958000 | H8: =C8/F8 -> 26800000 | I8: =G8/F8 -> -3183200
A9: Благотворительные фонды | B9: 0 - 5 | C9: 366217000 | D9: 363962000 | E9: =VLOOKUP(B9,Лист2!A:E,5,0) -> малые | F9: =VLOOKUP(B9,Лист2!A:E,4,0) -> 2.5 | G9: =C9-D9 -> 2255000 | H9: =C9/F9 -> 146486800 | I9: =G9/F9 -> 902000
A10: Общественные фонды | B10: 51 - 100 | C10: 253031000 | D10: 256576000 | E10: =VLOOKUP(B10,Лист2!A:E,5,0) -> средние | F10: =VLOOKUP(B10,Лист2!A:E,4,0) -> 75.5 | G10: =C10-D10 -> -3545000 | H10: =C10/F10 -> 3351404 | I10: =G10/F10 -> -46953.642
A11: Благотворительные фонды | B11: 0 - 5 | C11: 18169000 | D11: 15809000 | E11: =VLOOKUP(B11,Лист2!A:E,5,0) -> малые | F11: =VLOOKUP(B11,Лист2!A:E,4,0) -> 2.5 | G11: =C11-D11 -> 2360000 | H11: =C11/F11 -> 7267600 | I11: =G11/F11 -> 944000
A12: Общественные фонды | B12: 11 - 15 | C12: 191006000 | D12: 207475000 | E12: =VLOOKUP(B12,Лист2!A:E,5,0) -> малые | F12: =VLOOKUP(B12,Лист2!A:E,4,0) -> 13 | G12: =C12-D12 -> -16469000 | H12: =C12/F12 -> 14692769 | I12: =G12/F12 -> -1266846.2
A13: Благотворительные фонды | B13: 51 - 100 | C13: 128983000 | D13: 95513000 | E13: =VLOOKUP(B13,Лист2!A:E,5,0) -> средние | F13: =VLOOKUP(B13,Лист2!A:E,4,0) -> 75.5 | G13: =C13-D13 -> 33470000 | H13: =C13/F13 -> 1708384.1 | I13: =G13/F13 -> 443311.26
... A1771: Благотворительные фонды | B1771: 201 - 250 | C1771: 995636000 | D1771: 985164000 | E1771: =VLOOKUP(B1771,Лист2!A:E,5,0) -> крупные | F1771: =VLOOKUP(B1771,Лист2!A:E,4,0) -> 225.5 | G1771: =C1771-D1771 -> 10472000 | H1771: =C1771/F1771 -> 4415237.3 | I1771: =G1771/F1771 -> 46439.024

Sheet Лист2
A1: 0 - 5 | B1: 0 | C1: 5 | D1: =AVERAGE(B1:C1) -> 2.5 | E1: малые | L1: Благотворительные фонды
A2: 6 - 10 | B2: 6 | C2: 10 | D2: =AVERAGE(B2:C2) -> 8 | E2: малые | L2: Общественные фонды
A3: 11 - 15 | B3: 11 | C3: 15 | D3: =AVERAGE(B3:C3) -> 13 | E3: малые | L3: Фонды
A4: 51 - 100 | B4: 51 | C4: 100 | D4: =AVERAGE(B4:C4) -> 75.5 | E4: средние | L4: Экологические фонды
A5: 101 - 150 | B5: 101 | C5: 150 | D5: =AVERAGE(B5:C5) -> 125.5 | E5: средние | L5: Общественные организации
A6: 151 - 200 | B6: 151 | C6: 200 | D6: =AVERAGE(B6:C6) -> 175.5 | E6: средние
A7: 201 - 250 | B7: 201 | C7: 250 | D7: =AVERAGE(B7:C7) -> 225.5 | E7: крупные
A8: 251 - 500 | B8: 251 | C8: 500 | D8: =AVERAGE(B8:C8) -> 375.5 | E8: крупные
A9: 501 - 1 000 | B9: 501 | C9: 1000 | D9: =AVERAGE(B9:C9) -> 750.5 | E9: крупные
